dispersion/__init__.py
dispersion/catalogue.py
dispersion/config.py
dispersion/io.py
dispersion/material.py
dispersion/spectral_data.py
dispersion/spectrum.py
dispersion/scripts/__init__.py
dispersion/scripts/catalogue_rebuild.py
dispersion/scripts/setup_dispersion.py
dispersion-1.0.6.dist-info/LICENSE
dispersion-1.0.6.dist-info/METADATA
dispersion-1.0.6.dist-info/WHEEL
dispersion-1.0.6.dist-info/entry_points.txt
dispersion-1.0.6.dist-info/top_level.txt
dispersion-1.0.6.dist-info/RECORD
