Metadata-Version: 2.1
Name: dispersion
Version: 1.0.6
Summary: support for libraries of optical dispersion (refractive index) data files
Home-page: https://github.com/nano-sippe/dispersion
Author: Phillip Manley
Author-email: manley@zib.de
Classifier: Programming Language :: Python :: 3
Classifier: License :: OSI Approved :: MIT License
Classifier: Operating System :: OS Independent
Requires-Python: >=3.6
License-File: LICENSE
Requires-Dist: numpy
Requires-Dist: matplotlib
Requires-Dist: pandas
Requires-Dist: scipy
Requires-Dist: PyYAML
